setup.py
files/__init__.py
files/one.py
files/two.py
sonder.egg-info/PKG-INFO
sonder.egg-info/SOURCES.txt
sonder.egg-info/dependency_links.txt
sonder.egg-info/top_level.txt