Metadata-Version: 2.1
Name: sonder
Version: 0.0.1
Summary: My First Package
Author: Konstantinov AP
Author-email: mralexey111@gmail.com
